ttrw/__init__.py
ttrw/__main__.py
ttrw/main.py
ttrw/dictionaries/__init__.py
ttrw/dictionaries/dict_loader.py
ttrw/dictionaries/en/LICENSE
ttrw/dictionaries/en/adjectives.txt
ttrw/dictionaries/en/adverbs.txt
ttrw/dictionaries/en/nouns.txt
ttrw/dictionaries/pl/LICENSE
ttrw/dictionaries/pl/adjectives.txt
ttrw/dictionaries/pl/adverbs.txt
ttrw/dictionaries/pl/nouns.txt
ttrw-1.3.dist-info/LICENSE
ttrw-1.3.dist-info/METADATA
ttrw-1.3.dist-info/WHEEL
ttrw-1.3.dist-info/top_level.txt
ttrw-1.3.dist-info/RECORD
