Metadata-Version: 2.1
Name: ttrw
Version: 1.3
Summary: Simple python package that generates strings with randomly selected words.
Home-page: https://github.com/ttomasz/ttrw
Author: Tomasz Taraś
Author-email: tomasztaras@outlook.com
License: UNKNOWN
Platform: UNKNOWN
Classifier: Programming Language :: Python :: 3
Classifier: License :: OSI Approved :: MIT License
Classifier: Operating System :: OS Independent
